aya_py/__init__.py
kst_pip_test-1.0.8.dist-info/LICENSE
kst_pip_test-1.0.8.dist-info/METADATA
kst_pip_test-1.0.8.dist-info/WHEEL
kst_pip_test-1.0.8.dist-info/top_level.txt
kst_pip_test-1.0.8.dist-info/RECORD
