Metadata-Version: 2.1
Name: kst-pip-test
Version: 1.0.8
Summary: A small example package
Author: Khant Si Thu @ Aaron Chen
Author-email: dev.kst.aaron@gmail.com
Classifier: Programming Language :: Python :: 3
Classifier: License :: OSI Approved :: MIT License
Classifier: Operating System :: OS Independent
Requires-Python: >=3.6
License-File: LICENSE
Requires-Dist: requests (>=2.28.1)
Requires-Dist: pycryptodome (>=3.15.0)
